openAI_original/__init__.py
openAI_original/main.py
openai_original-0.1.0.dist-info/licenses/LICENSE
openai_original-0.1.0.dist-info/METADATA
openai_original-0.1.0.dist-info/WHEEL
openai_original-0.1.0.dist-info/top_level.txt
openai_original-0.1.0.dist-info/RECORD
