Metadata-Version: 2.4
Name: openAI_original
Version: 0.1.0
Summary: Original Open AI library
Author-email: Jahongir <yusupovj859@example.com>
License: MIT
Requires-Python: >=3.7
License-File: LICENSE
Dynamic: license-file
